{
  "livros": [
    {
      "id": 1,
      "titulo": "O Principe",
      "autor_id": 1,
      "genero_id": 1
    },
    {
      "id": 2,
      "titulo": "A Arte da Guerra",
      "autor_id": 2,
      "genero_id": 1
    },
    {
      "id": 3,
      "titulo": "Malleus Maleficarum",
      "autor_id": 3,
      "genero_id": 1
    },
    {
      "id": 4,
      "titulo": "Fogo & Sangue",
      "autor_id": 4,
      "genero_id": 4
    }

  ],
  "autor": [
    {
      "id": 1,
      "nome": "Nicolau Maquiavel"
    },
    {
      "id": 2,
      "nome": "Sun Tzu"
    },
    {
      "id": 3,
      "nome": "Heinrich Kraemer"
    },
    {
      "id": 4,
      "nome": "George R.R. Martin"
    }

  ],
  "genero": [
    {
      "id": 1,
      "tipo": "Não ficção"
    },
    {
      "id": 2,
      "tipo": "Romance"
    },
    {
      "id": 3,
      "tipo": "Fantasia"
    },
    {
      "id": 4,
      "tipo": "Ficção"
    }

  ]

}